pytractive/__init__.py
pytractive/api.py
pytractive/channel.py
pytractive/data_object.py
pytractive/exceptions.py
pytractive/trackable_object.py
pytractive/tracker.py
pytractive/tractive.py
pytractive-1.1.0.dist-info/WHEEL
pytractive-1.1.0.dist-info/entry_points.txt
pytractive-1.1.0.dist-info/METADATA
pytractive-1.1.0.dist-info/RECORD
