Metadata-Version: 2.3
Name: pytractive
Version: 1.1.0
Summary: Unofficial Asynchronous Python client for the Tractive REST API.
Author: Wolfhound
Author-email: Wolfhound <contact@wolfhound.dev>
Requires-Dist: aiohttp>=3.12.15
Requires-Dist: asyncio>=4.0.0
Requires-Python: >=3.13
